simplejrpc_gbox/__init__.py
simplejrpc_gbox/_date.py
simplejrpc_gbox/_decode.py
simplejrpc_gbox/_encode.py
simplejrpc_gbox/_file.py
simplejrpc_gbox/_fnctl.py
simplejrpc_gbox/_sort.py
simplejrpc_gbox/_system.py
simplejrpc_gbox/cmd.py
simplejrpc_gbox/lazy.py
simplejrpc_gbox/strconv.py
simplejrpc_gbox-0.0.1.dist-info/LICENSE.txt
simplejrpc_gbox-0.0.1.dist-info/METADATA
simplejrpc_gbox-0.0.1.dist-info/WHEEL
simplejrpc_gbox-0.0.1.dist-info/RECORD
