Metadata-Version: 2.3
Name: simplejrpc_gbox
Version: 0.0.1
Summary: GM tools box
License: MIT
Author: yao
Author-email: 1125564921@qq.com
Requires-Python: >=3.10,<4.0
Classifier: License :: OSI Approved :: MIT License
Classifier: Programming Language :: Python :: 3
Classifier: Programming Language :: Python :: 3.10
Classifier: Programming Language :: Python :: 3.11
Classifier: Programming Language :: Python :: 3.12
Classifier: Programming Language :: Python :: 3.13
Requires-Dist: psutil (>=7.0.0,<8.0.0)
Requires-Dist: requests (>=2.32.3,<3.0.0)
